musicbrainzngs/__init__.py
musicbrainzngs/caa.py
musicbrainzngs/compat.py
musicbrainzngs/mbxml.py
musicbrainzngs/musicbrainz.py
musicbrainzngs/util.py
musicbrainzngs-0.7.dist-info/COPYING
musicbrainzngs-0.7.dist-info/METADATA
musicbrainzngs-0.7.dist-info/WHEEL
musicbrainzngs-0.7.dist-info/top_level.txt
musicbrainzngs-0.7.dist-info/RECORD
