Metadata-Version: 2.1
Name: musicbrainzngs
Version: 0.7
Summary: Python bindings for the MusicBrainz NGS and the Cover Art Archive webservices
Home-page: https://python-musicbrainzngs.readthedocs.org/
Author: Alastair Porter
Author-email: alastair@porter.net.nz
License: BSD 2-clause
Platform: UNKNOWN
Classifier: Development Status :: 5 - Production/Stable
Classifier: License :: OSI Approved :: BSD License
Classifier: License :: OSI Approved :: ISC License (ISCL)
Classifier: Intended Audience :: Developers
Classifier: Operating System :: OS Independent
Classifier: Programming Language :: Python
Classifier: Topic :: Database :: Front-Ends
Classifier: Topic :: Software Development :: Libraries :: Python Modules
Requires-Python: >=2.7, !=3.0.*, !=3.1.*, !=3.2.*, !=3.3.*
